[
  {
    "Index": 1,
    "Timestamp": 1749481116.1721566,
    "Time": "2025-06-09 14:58:36.172",
    "ECUId": "SIM_ECU_01",
    "ApID": "SYSTEM",
    "CtID": "BOOT",
    "SessionID": 1749488250,
    "Type": "LOG",
    "LogLevel": "INFO",
    "Payload": "Dummy Automotive Application STARTING. Version: 1.0.1 (fixed)."
  },
  {
    "Index": 2,
    "Timestamp": 1749481116.173437,
    "Time": "2025-06-09 14:58:36.173",
    "ECUId": "SIM_ECU_01",
    "ApID": "SYSTEM",
    "CtID": "BOOT",
    "SessionID": 1749488250,
    "Type": "LOG",
    "LogLevel": "INFO",
    "Payload": "App started with 87 arguments. First arg: 'argv [ 1 ]'."
  },
  {
    "Index": 3,
    "Timestamp": 1749481116.175704,
    "Time": "2025-06-09 14:58:36.175",
    "ECUId": "SIM_ECU_01",
    "ApID": "SYSTEM",
    "CtID": "BOOT",
    "SessionID": 1749488250,
    "Type": "LOG",
    "LogLevel": "INFO",
    "Payload": "App started with no command-line arguments."
  },
  {
    "Index": 4,
    "Timestamp": 1749481116.1826425,
    "Time": "2025-06-09 14:58:36.182",
    "ECUId": "SIM_ECU_01",
    "ApID": "SYSTEM",
    "CtID": "MAIN",
    "SessionID": 1749488250,
    "Type": "LOG",
    "LogLevel": "DEBUG",
    "Payload": "Creating VehicleController instance..."
  },
  {
    "Index": 5,
    "Timestamp": 1749481116.1848352,
    "Time": "2025-06-09 14:58:36.184",
    "ECUId": "SIM_ECU_01",
    "ApID": "SYSTEM",
    "CtID": "MAIN",
    "SessionID": 1749488250,
    "Type": "LOG",
    "LogLevel": "DEBUG",
    "Payload": "VehicleController instance created."
  },
  {
    "Index": 6,
    "Timestamp": 1749481116.1971543,
    "Time": "2025-06-09 14:58:36.197",
    "ECUId": "SIM_ECU_01",
    "ApID": "SYSTEM",
    "CtID": "MAIN",
    "SessionID": 1749488250,
    "Type": "LOG",
    "LogLevel": "INFO",
    "Payload": "Initiating system initialization sequence..."
  },
  {
    "Index": 7,
    "Timestamp": 1749481116.2102964,
    "Time": "2025-06-09 14:58:36.210",
    "ECUId": "SIM_ECU_01",
    "ApID": "VCTRL",
    "CtID": "START",
    "SessionID": 1749488250,
    "Type": "LOG",
    "LogLevel": "INFO",
    "Payload": "Vehicle system initialization: STARTED."
  },
  {
    "Index": 8,
    "Timestamp": 1749481116.2130551,
    "Time": "2025-06-09 14:58:36.213",
    "ECUId": "SIM_ECU_01",
    "ApID": "VCTRL",
    "CtID": "PWR",
    "SessionID": 1749488250,
    "Type": "LOG",
    "LogLevel": "INFO",
    "Payload": "Performing Power-On Self-Test (POST)."
  },
  {
    "Index": 9,
    "Timestamp": 1749481116.2149136,
    "Time": "2025-06-09 14:58:36.214",
    "ECUId": "SIM_ECU_01",
    "ApID": "VCTRL",
    "CtID": "PWR",
    "SessionID": 1749488250,
    "Type": "LOG",
    "LogLevel": "DEBUG",
    "Payload": "Main ECU voltage: 12.6V (OK)."
  },
  {
    "Index": 10,
    "Timestamp": 1749481116.2286885,
    "Time": "2025-06-09 14:58:36.228",
    "ECUId": "SIM_ECU_01",
    "ApID": "VCTRL",
    "CtID": "PWR",
    "SessionID": 1749488250,
    "Type": "LOG",
    "LogLevel": "DEBUG",
    "Payload": "CAN bus A termination: 60 Ohm (Nominal)."
  },
  {
    "Index": 11,
    "Timestamp": 1749481116.2396119,
    "Time": "2025-06-09 14:58:36.239",
    "ECUId": "SIM_ECU_01",
    "ApID": "VCTRL",
    "CtID": "PWR",
    "SessionID": 1749488250,
    "Type": "LOG",
    "LogLevel": "DEBUG",
    "Payload": "CAN bus B termination: 60 Ohm (Nominal)."
  },
  {
    "Index": 12,
    "Timestamp": 1749481116.2526438,
    "Time": "2025-06-09 14:58:36.252",
    "ECUId": "SIM_ECU_01",
    "ApID": "VCTRL",
    "CtID": "PWR",
    "SessionID": 1749488250,
    "Type": "LOG",
    "LogLevel": "INFO",
    "Payload": "POST completed successfully."
  },
  {
    "Index": 13,
    "Timestamp": 1749481116.2582724,
    "Time": "2025-06-09 14:58:36.258",
    "ECUId": "SIM_ECU_01",
    "ApID": "VCTRL",
    "CtID": "START",
    "SessionID": 1749488250,
    "Type": "LOG",
    "LogLevel": "ERROR",
    "Payload": "ERROR: TCU init FAILED. Limited functionality."
  },
  {
    "Index": 14,
    "Timestamp": 1749481116.2695637,
    "Time": "2025-06-09 14:58:36.269",
    "ECUId": "SIM_ECU_01",
    "ApID": "VCTRL",
    "CtID": "START",
    "SessionID": 1749488250,
    "Type": "LOG",
    "LogLevel": "ERROR",
    "Payload": "ERROR: ABS init FAILED."
  },
  {
    "Index": 15,
    "Timestamp": 1749481116.27933,
    "Time": "2025-06-09 14:58:36.279",
    "ECUId": "SIM_ECU_01",
    "ApID": "VCTRL",
    "CtID": "START",
    "SessionID": 1749488250,
    "Type": "LOG",
    "LogLevel": "ERROR",
    "Payload": "ERROR: BCM init FAILED."
  },
  {
    "Index": 16,
    "Timestamp": 1749481116.2896962,
    "Time": "2025-06-09 14:58:36.289",
    "ECUId": "SIM_ECU_01",
    "ApID": "VCTRL",
    "CtID": "START",
    "SessionID": 1749488250,
    "Type": "LOG",
    "LogLevel": "WARN",
    "Payload": "WARNING: IHU init FAILED. User experience affected."
  },
  {
    "Index": 17,
    "Timestamp": 1749481116.2926135,
    "Time": "2025-06-09 14:58:36.292",
    "ECUId": "SIM_ECU_01",
    "ApID": "VCTRL",
    "CtID": "START",
    "SessionID": 1749488250,
    "Type": "LOG",
    "LogLevel": "INFO",
    "Payload": "Vehicle system initialization: COMPLETED. State: RUNNING (2)."
  },
  {
    "Index": 18,
    "Timestamp": 1749481116.3016133,
    "Time": "2025-06-09 14:58:36.301",
    "ECUId": "SIM_ECU_01",
    "ApID": "VCTRL",
    "CtID": "START",
    "SessionID": 1749488250,
    "Type": "LOG",
    "LogLevel": "ERROR",
    "Payload": "Vehicle system initialization: FAILED. State: ERROR (3). See logs."
  },
  {
    "Index": 19,
    "Timestamp": 1749481116.3078268,
    "Time": "2025-06-09 14:58:36.307",
    "ECUId": "SIM_ECU_01",
    "ApID": "VCTRL",
    "CtID": "NET",
    "SessionID": 1749488250,
    "Type": "LOG",
    "LogLevel": "INFO",
    "Payload": "Broadcasting network frame: System Active. Node ID: 0x01 (VCTRL)."
  },
  {
    "Index": 20,
    "Timestamp": 1749481116.3165298,
    "Time": "2025-06-09 14:58:36.316",
    "ECUId": "SIM_ECU_01",
    "ApID": "VCTRL",
    "CtID": "COMM",
    "SessionID": 1749488250,
    "Type": "LOG",
    "LogLevel": "DEBUG",
    "Payload": "Sending heartbeat on CAN Bus A. Cycle: 100ms (Simulated)."
  },
  {
    "Index": 21,
    "Timestamp": 1749481116.331402,
    "Time": "2025-06-09 14:58:36.331",
    "ECUId": "SIM_ECU_01",
    "ApID": "SYSTEM",
    "CtID": "MAIN",
    "SessionID": 1749488250,
    "Type": "LOG",
    "LogLevel": "INFO",
    "Payload": "System initialization sequence finished by VehicleController."
  },
  {
    "Index": 22,
    "Timestamp": 1749481116.3344607,
    "Time": "2025-06-09 14:58:36.334",
    "ECUId": "SIM_ECU_01",
    "ApID": "SYSTEM",
    "CtID": "MAIN",
    "SessionID": 1749488250,
    "Type": "LOG",
    "LogLevel": "INFO",
    "Payload": "Entering main application loop (simulated 2 iterations)."
  },
  {
    "Index": 23,
    "Timestamp": 1749481116.3363204,
    "Time": "2025-06-09 14:58:36.336",
    "ECUId": "SIM_ECU_01",
    "ApID": "SYSTEM",
    "CtID": "LOOP",
    "SessionID": 1749488250,
    "Type": "LOG",
    "LogLevel": "DEBUG",
    "Payload": "Main loop - Iteration #45."
  },
  {
    "Index": 24,
    "Timestamp": 1749481116.341463,
    "Time": "2025-06-09 14:58:36.341",
    "ECUId": "SIM_ECU_01",
    "ApID": "VCTRL",
    "CtID": "LOOP",
    "SessionID": 1749488250,
    "Type": "LOG",
    "LogLevel": "WARN",
    "Payload": "Main loop skipped. System not init or not RUNNING. Current State val: 85."
  },
  {
    "Index": 25,
    "Timestamp": 1749481116.3428106,
    "Time": "2025-06-09 14:58:36.342",
    "ECUId": "SIM_ECU_01",
    "ApID": "VCTRL",
    "CtID": "LOOP",
    "SessionID": 1749488250,
    "Type": "LOG",
    "LogLevel": "DEBUG",
    "Payload": "Running main vehicle loop iteration. Vehicle State val: 59."
  },
  {
    "Index": 26,
    "Timestamp": 1749481116.352565,
    "Time": "2025-06-09 14:58:36.352",
    "ECUId": "SIM_ECU_01",
    "ApID": "ECM",
    "CtID": "PROC",
    "SessionID": 1749488250,
    "Type": "LOG",
    "LogLevel": "WARN",
    "Payload": "ProcessEngineData: Module not initialized. Skipping."
  },
  {
    "Index": 27,
    "Timestamp": 1749481116.3551354,
    "Time": "2025-06-09 14:58:36.355",
    "ECUId": "SIM_ECU_01",
    "ApID": "ECM",
    "CtID": "PROC",
    "SessionID": 1749488250,
    "Type": "LOG",
    "LogLevel": "DEBUG",
    "Payload": "Processing Petrol engine data. Sim-RPM: 1500, Sim-Coolant: 85.5C."
  },
  {
    "Index": 28,
    "Timestamp": 1749481116.3654602,
    "Time": "2025-06-09 14:58:36.365",
    "ECUId": "SIM_ECU_01",
    "ApID": "ECM",
    "CtID": "PROC",
    "SessionID": 1749488250,
    "Type": "LOG",
    "LogLevel": "DEBUG",
    "Payload": "Processing Diesel engine data. Sim-RPM: 1200, Sim-Coolant: 90.1C."
  },
  {
    "Index": 29,
    "Timestamp": 1749481116.3784444,
    "Time": "2025-06-09 14:58:36.378",
    "ECUId": "SIM_ECU_01",
    "ApID": "ECM",
    "CtID": "PROC",
    "SessionID": 1749488250,
    "Type": "LOG",
    "LogLevel": "DEBUG",
    "Payload": "Processing Electric motor data. Sim-Power: 25kW, Sim-BattTemp: 35.2C."
  },
  {
    "Index": 30,
    "Timestamp": 1749481116.3800476,
    "Time": "2025-06-09 14:58:36.380",
    "ECUId": "SIM_ECU_01",
    "ApID": "ECM",
    "CtID": "SENSOR",
    "SessionID": 1749488250,
    "Type": "LOG",
    "LogLevel": "DEBUG",
    "Payload": "Checking engine sensors. SimValues: O2=0.85V (Rich), MAF=15.2g/s (Nominal), Coolant=88.1C (Normal)."
  },
  {
    "Index": 31,
    "Timestamp": 1749481116.3869529,
    "Time": "2025-06-09 14:58:36.386",
    "ECUId": "SIM_ECU_01",
    "ApID": "ECM",
    "CtID": "SENSOR",
    "SessionID": 1749488250,
    "Type": "LOG",
    "LogLevel": "ERROR",
    "Payload": "CRITICAL: Engine overheating! Coolant Temp: 107.2C. Max Temp: 105.0C."
  },
  {
    "Index": 32,
    "Timestamp": 1749481116.3913915,
    "Time": "2025-06-09 14:58:36.391",
    "ECUId": "SIM_ECU_01",
    "ApID": "ECM",
    "CtID": "FUEL",
    "SessionID": 1749488250,
    "Type": "LOG",
    "LogLevel": "DEBUG",
    "Payload": "Fuel injection N/A for electric motor (Type 2)."
  },
  {
    "Index": 33,
    "Timestamp": 1749481116.3953378,
    "Time": "2025-06-09 14:58:36.395",
    "ECUId": "SIM_ECU_01",
    "ApID": "ECM",
    "CtID": "FUEL",
    "SessionID": 1749488250,
    "Type": "LOG",
    "LogLevel": "INFO",
    "Payload": "Enabling fuel injection. System: Common Rail."
  },
  {
    "Index": 34,
    "Timestamp": 1749481116.3979776,
    "Time": "2025-06-09 14:58:36.397",
    "ECUId": "SIM_ECU_01",
    "ApID": "ECM",
    "CtID": "FUEL",
    "SessionID": 1749488250,
    "Type": "LOG",
    "LogLevel": "INFO",
    "Payload": "Disabling fuel injection. Reason: Shutdown/Overheat."
  },
  {
    "Index": 35,
    "Timestamp": 1749481116.4053469,
    "Time": "2025-06-09 14:58:36.405",
    "ECUId": "SIM_ECU_01",
    "ApID": "ECM",
    "CtID": "FUEL",
    "SessionID": 1749488250,
    "Type": "LOG",
    "LogLevel": "WARN",
    "Payload": "Overheat protection: Fuel injection DISABLED."
  },
  {
    "Index": 36,
    "Timestamp": 1749481116.4148424,
    "Time": "2025-06-09 14:58:36.414",
    "ECUId": "SIM_ECU_01",
    "ApID": "ECM",
    "CtID": "SENSOR",
    "SessionID": 1749488250,
    "Type": "LOG",
    "LogLevel": "WARN",
    "Payload": "Engine temperature high: 98.5C. Normal Max: 95.0C."
  },
  {
    "Index": 37,
    "Timestamp": 1749481116.4288068,
    "Time": "2025-06-09 14:58:36.428",
    "ECUId": "SIM_ECU_01",
    "ApID": "ECM",
    "CtID": "IGNIT",
    "SessionID": 1749488250,
    "Type": "LOG",
    "LogLevel": "DEBUG",
    "Payload": "Ignition control N/A for electric motor (Type 2)."
  },
  {
    "Index": 38,
    "Timestamp": 1749481116.4398756,
    "Time": "2025-06-09 14:58:36.439",
    "ECUId": "SIM_ECU_01",
    "ApID": "ECM",
    "CtID": "IGNIT",
    "SessionID": 1749488250,
    "Type": "LOG",
    "LogLevel": "INFO",
    "Payload": "Enabling ignition system. Type: Coil-on-Plug."
  },
  {
    "Index": 39,
    "Timestamp": 1749481116.442614,
    "Time": "2025-06-09 14:58:36.442",
    "ECUId": "SIM_ECU_01",
    "ApID": "ECM",
    "CtID": "IGNIT",
    "SessionID": 1749488250,
    "Type": "LOG",
    "LogLevel": "INFO",
    "Payload": "Disabling ignition system. Reason: Shutdown/Over-rev."
  },
  {
    "Index": 40,
    "Timestamp": 1749481116.4518855,
    "Time": "2025-06-09 14:58:36.451",
    "ECUId": "SIM_ECU_01",
    "ApID": "ECM",
    "CtID": "IGNIT",
    "SessionID": 1749488250,
    "Type": "LOG",
    "LogLevel": "ERROR",
    "Payload": "Over-rev protection: Ignition system DISABLED."
  },
  {
    "Index": 41,
    "Timestamp": 1749481116.455113,
    "Time": "2025-06-09 14:58:36.455",
    "ECUId": "SIM_ECU_01",
    "ApID": "ECM",
    "CtID": "PROC",
    "SessionID": 1749488250,
    "Type": "LOG",
    "LogLevel": "DEBUG",
    "Payload": "Updating engine actuators. SimActions: Throttle=15pct (Actual 14.8pct)."
  },
  {
    "Index": 42,
    "Timestamp": 1749481116.4678378,
    "Time": "2025-06-09 14:58:36.467",
    "ECUId": "SIM_ECU_01",
    "ApID": "ECM",
    "CtID": "PROC",
    "SessionID": 1749488250,
    "Type": "LOG",
    "LogLevel": "INFO",
    "Payload": "Cooling fan command: ON (High Speed L2). SimCoolant: 96.0C."
  },
  {
    "Index": 43,
    "Timestamp": 1749481116.4724863,
    "Time": "2025-06-09 14:58:36.472",
    "ECUId": "SIM_ECU_01",
    "ApID": "ECM",
    "CtID": "PROC",
    "SessionID": 1749488250,
    "Type": "LOG",
    "LogLevel": "INFO",
    "Payload": "Cooling fan command: OFF. SimCoolant: 85.0C."
  },
  {
    "Index": 44,
    "Timestamp": 1749481116.4747424,
    "Time": "2025-06-09 14:58:36.474",
    "ECUId": "SIM_ECU_01",
    "ApID": "ECM",
    "CtID": "PROC",
    "SessionID": 1749488250,
    "Type": "LOG",
    "LogLevel": "DEBUG",
    "Payload": "Finished processing engine data. Cycle time: 10 ms (simulated)."
  },
  {
    "Index": 45,
    "Timestamp": 1749481116.482303,
    "Time": "2025-06-09 14:58:36.482",
    "ECUId": "SIM_ECU_01",
    "ApID": "TCU",
    "CtID": "PROC",
    "SessionID": 1749488250,
    "Type": "LOG",
    "LogLevel": "WARN",
    "Payload": "ProcessTransmissionRequests: Module not initialized. Skipping."
  },
  {
    "Index": 46,
    "Timestamp": 1749481116.4939296,
    "Time": "2025-06-09 14:58:36.493",
    "ECUId": "SIM_ECU_01",
    "ApID": "TCU",
    "CtID": "PROC",
    "SessionID": 1749488250,
    "Type": "LOG",
    "LogLevel": "DEBUG",
    "Payload": "Automatic: Processing shift logic. Sim-RPM: 2200, Sim-Speed: 60km/h."
  },
  {
    "Index": 47,
    "Timestamp": 1749481116.502114,
    "Time": "2025-06-09 14:58:36.502",
    "ECUId": "SIM_ECU_01",
    "ApID": "TCU",
    "CtID": "GEAR",
    "SessionID": 1749488250,
    "Type": "LOG",
    "LogLevel": "WARN",
    "Payload": "ShiftGearUp ignored. Reason: Not Auto or Not Initialized."
  },
  {
    "Index": 48,
    "Timestamp": 1749481116.5163095,
    "Time": "2025-06-09 14:58:36.516",
    "ECUId": "SIM_ECU_01",
    "ApID": "TCU",
    "CtID": "GEAR",
    "SessionID": 1749488250,
    "Type": "LOG",
    "LogLevel": "INFO",
    "Payload": "Shifted UP. New gear: 22."
  },
  {
    "Index": 49,
    "Timestamp": 1749481116.5310535,
    "Time": "2025-06-09 14:58:36.531",
    "ECUId": "SIM_ECU_01",
    "ApID": "TCU",
    "CtID": "GEAR",
    "SessionID": 1749488250,
    "Type": "LOG",
    "LogLevel": "INFO",
    "Payload": "Already in highest gear (6). Shift up ignored."
  },
  {
    "Index": 50,
    "Timestamp": 1749481116.542646,
    "Time": "2025-06-09 14:58:36.542",
    "ECUId": "SIM_ECU_01",
    "ApID": "TCU",
    "CtID": "GEAR",
    "SessionID": 1749488250,
    "Type": "LOG",
    "LogLevel": "DEBUG",
    "Payload": "Controlling shift solenoids for gear: 100."
  },
  {
    "Index": 51,
    "Timestamp": 1749481116.5519338,
    "Time": "2025-06-09 14:58:36.551",
    "ECUId": "SIM_ECU_01",
    "ApID": "TCU",
    "CtID": "GEAR",
    "SessionID": 1749488250,
    "Type": "LOG",
    "LogLevel": "DEBUG",
    "Payload": "Solenoid A: ON, Solenoid B: OFF (For Gear 1)."
  },
  {
    "Index": 52,
    "Timestamp": 1749481116.5628555,
    "Time": "2025-06-09 14:58:36.562",
    "ECUId": "SIM_ECU_01",
    "ApID": "TCU",
    "CtID": "PROC",
    "SessionID": 1749488250,
    "Type": "LOG",
    "LogLevel": "DEBUG",
    "Payload": "Manual: Awaiting gear shift. Clutch pos: 90pct (Engaged sim)."
  },
  {
    "Index": 53,
    "Timestamp": 1749481116.5684626,
    "Time": "2025-06-09 14:58:36.568",
    "ECUId": "SIM_ECU_01",
    "ApID": "TCU",
    "CtID": "HYDRAU",
    "SessionID": 1749488250,
    "Type": "LOG",
    "LogLevel": "ERROR",
    "Payload": "CRITICAL: Transmission oil OVERHEATING! Temp: 122.5C. Max: 120.0C."
  },
  {
    "Index": 54,
    "Timestamp": 1749481116.5761867,
    "Time": "2025-06-09 14:58:36.576",
    "ECUId": "SIM_ECU_01",
    "ApID": "TCU",
    "CtID": "STATE",
    "SessionID": 1749488250,
    "Type": "LOG",
    "LogLevel": "WARN",
    "Payload": "Transmission safe state requested. Forcing Neutral."
  },
  {
    "Index": 55,
    "Timestamp": 1749481116.585776,
    "Time": "2025-06-09 14:58:36.585",
    "ECUId": "SIM_ECU_01",
    "ApID": "TCU",
    "CtID": "STATE",
    "SessionID": 1749488250,
    "Type": "LOG",
    "LogLevel": "INFO",
    "Payload": "Transmission now in Neutral (Safe State). SimOilTemp: 23.4C."
  },
  {
    "Index": 56,
    "Timestamp": 1749481116.5958202,
    "Time": "2025-06-09 14:58:36.595",
    "ECUId": "SIM_ECU_01",
    "ApID": "TCU",
    "CtID": "HYDRAU",
    "SessionID": 1749488250,
    "Type": "LOG",
    "LogLevel": "WARN",
    "Payload": "Transmission oil temperature HIGH: 105.0C. Recommended Max: 100.0C."
  },
  {
    "Index": 57,
    "Timestamp": 1749481116.6033194,
    "Time": "2025-06-09 14:58:36.603",
    "ECUId": "SIM_ECU_01",
    "ApID": "TCU",
    "CtID": "PROC",
    "SessionID": 1749488250,
    "Type": "LOG",
    "LogLevel": "DEBUG",
    "Payload": "Finished processing transmission requests for this cycle."
  },
  {
    "Index": 58,
    "Timestamp": 1749481116.610412,
    "Time": "2025-06-09 14:58:36.610",
    "ECUId": "SIM_ECU_01",
    "ApID": "ABS",
    "CtID": "PROC",
    "SessionID": 1749488250,
    "Type": "LOG",
    "LogLevel": "WARN",
    "Payload": "MonitorWheelSpeeds: Module not initialized. Skipping."
  },
  {
    "Index": 59,
    "Timestamp": 1749481116.62322,
    "Time": "2025-06-09 14:58:36.623",
    "ECUId": "SIM_ECU_01",
    "ApID": "ABS",
    "CtID": "WHEEL",
    "SessionID": 1749488250,
    "Type": "LOG",
    "LogLevel": "DEBUG",
    "Payload": "Wheel Speeds (km/h): FL=50.2, FR=50.1, RL=49.8, RR=25.5 (Simulated)."
  },
  {
    "Index": 60,
    "Timestamp": 1749481116.6320693,
    "Time": "2025-06-09 14:58:36.632",
    "ECUId": "SIM_ECU_01",
    "ApID": "ABS",
    "CtID": "WHEEL",
    "SessionID": 1749488250,
    "Type": "LOG",
    "LogLevel": "WARN",
    "Payload": "Significant speed diff for RR wheel (25.5 km/h vs avg 50.1 km/h). Possible slippage/sensor issue."
  },
  {
    "Index": 61,
    "Timestamp": 1749481116.6439247,
    "Time": "2025-06-09 14:58:36.643",
    "ECUId": "SIM_ECU_01",
    "ApID": "ABS",
    "CtID": "PUMP",
    "SessionID": 1749488250,
    "Type": "LOG",
    "LogLevel": "INFO",
    "Payload": "ABS Pump activated. Modulating brake pressure for RR wheel. Target slip: 15pct (sim)."
  },
  {
    "Index": 62,
    "Timestamp": 1749481116.6491523,
    "Time": "2025-06-09 14:58:36.649",
    "ECUId": "SIM_ECU_01",
    "ApID": "ABS",
    "CtID": "WHEEL",
    "SessionID": 1749488250,
    "Type": "LOG",
    "LogLevel": "INFO",
    "Payload": "Wheel speeds stabilized. ABS deactivated."
  },
  {
    "Index": 63,
    "Timestamp": 1749481116.6616378,
    "Time": "2025-06-09 14:58:36.661",
    "ECUId": "SIM_ECU_01",
    "ApID": "ABS",
    "CtID": "STABIL",
    "SessionID": 1749488250,
    "Type": "LOG",
    "LogLevel": "INFO",
    "Payload": "ESP intervention: Understeer detected. Applying brake to FR wheel (20 bar sim)."
  },
  {
    "Index": 64,
    "Timestamp": 1749481116.6682906,
    "Time": "2025-06-09 14:58:36.668",
    "ECUId": "SIM_ECU_01",
    "ApID": "ABS",
    "CtID": "STABIL",
    "SessionID": 1749488250,
    "Type": "LOG",
    "LogLevel": "INFO",
    "Payload": "ESP system managing stability. Sim Sensors: Yaw=5.2deg/s, Steering=15deg."
  },
  {
    "Index": 65,
    "Timestamp": 1749481116.6783373,
    "Time": "2025-06-09 14:58:36.678",
    "ECUId": "SIM_ECU_01",
    "ApID": "ABS",
    "CtID": "STABIL",
    "SessionID": 1749488250,
    "Type": "LOG",
    "LogLevel": "INFO",
    "Payload": "Corrupted data detected: val=-9999.99, status=0xFFFFFFFF"
  },
  {
    "Index": 66,
    "Timestamp": 1749481116.6794415,
    "Time": "2025-06-09 14:58:36.679",
    "ECUId": "SIM_ECU_01",
    "ApID": "ABS",
    "CtID": "PROC",
    "SessionID": 1749488250,
    "Type": "LOG",
    "LogLevel": "DEBUG",
    "Payload": "Finished monitoring wheel speeds for this cycle."
  },
  {
    "Index": 67,
    "Timestamp": 1749481116.6934621,
    "Time": "2025-06-09 14:58:36.693",
    "ECUId": "SIM_ECU_01",
    "ApID": "BCM",
    "CtID": "PROC",
    "SessionID": 1749488250,
    "Type": "LOG",
    "LogLevel": "WARN",
    "Payload": "ProcessComfortRequests: BCM not initialized. Skipping."
  },
  {
    "Index": 68,
    "Timestamp": 1749481116.703664,
    "Time": "2025-06-09 14:58:36.703",
    "ECUId": "SIM_ECU_01",
    "ApID": "BCM",
    "CtID": "PROC",
    "SessionID": 1749488250,
    "Type": "LOG",
    "LogLevel": "DEBUG",
    "Payload": "Processing comfort and access requests."
  },
  {
    "Index": 69,
    "Timestamp": 1749481116.7133672,
    "Time": "2025-06-09 14:58:36.713",
    "ECUId": "SIM_ECU_01",
    "ApID": "BCM",
    "CtID": "LIGHT",
    "SessionID": 1749488250,
    "Type": "LOG",
    "LogLevel": "INFO",
    "Payload": "Ambient light dark. Auto-activating headlights to ON (State 2)."
  },
  {
    "Index": 70,
    "Timestamp": 1749481116.7232165,
    "Time": "2025-06-09 14:58:36.723",
    "ECUId": "SIM_ECU_01",
    "ApID": "BCM",
    "CtID": "LIGHT",
    "SessionID": 1749488250,
    "Type": "LOG",
    "LogLevel": "INFO",
    "Payload": "Headlights set to OFF (State 0)."
  },
  {
    "Index": 71,
    "Timestamp": 1749481116.7301347,
    "Time": "2025-06-09 14:58:36.730",
    "ECUId": "SIM_ECU_01",
    "ApID": "BCM",
    "CtID": "LIGHT",
    "SessionID": 1749488250,
    "Type": "LOG",
    "LogLevel": "INFO",
    "Payload": "Headlights set to PARKING (State 1)."
  },
  {
    "Index": 72,
    "Timestamp": 1749481116.7417078,
    "Time": "2025-06-09 14:58:36.741",
    "ECUId": "SIM_ECU_01",
    "ApID": "BCM",
    "CtID": "LIGHT",
    "SessionID": 1749488250,
    "Type": "LOG",
    "LogLevel": "INFO",
    "Payload": "Headlights set to ON (State 2 - Low Beam)."
  },
  {
    "Index": 73,
    "Timestamp": 1749481116.749744,
    "Time": "2025-06-09 14:58:36.749",
    "ECUId": "SIM_ECU_01",
    "ApID": "BCM",
    "CtID": "LIGHT",
    "SessionID": 1749488250,
    "Type": "LOG",
    "LogLevel": "WARN",
    "Payload": "Invalid headlight state requested: 58. No action."
  },
  {
    "Index": 74,
    "Timestamp": 1749481116.7547016,
    "Time": "2025-06-09 14:58:36.754",
    "ECUId": "SIM_ECU_01",
    "ApID": "BCM",
    "CtID": "LIGHT",
    "SessionID": 1749488250,
    "Type": "LOG",
    "LogLevel": "DEBUG",
    "Payload": "LIN command sent to headlight module. New state: 27."
  },
  {
    "Index": 75,
    "Timestamp": 1749481116.7570481,
    "Time": "2025-06-09 14:58:36.757",
    "ECUId": "SIM_ECU_01",
    "ApID": "BCM",
    "CtID": "ACCESS",
    "SessionID": 1749488250,
    "Type": "LOG",
    "LogLevel": "INFO",
    "Payload": "Central locking request. Locking all doors."
  },
  {
    "Index": 76,
    "Timestamp": 1749481116.7714787,
    "Time": "2025-06-09 14:58:36.771",
    "ECUId": "SIM_ECU_01",
    "ApID": "BCM",
    "CtID": "ACCESS",
    "SessionID": 1749488250,
    "Type": "LOG",
    "LogLevel": "INFO",
    "Payload": "Locking all doors. Command: LOCK."
  },
  {
    "Index": 77,
    "Timestamp": 1749481116.7770715,
    "Time": "2025-06-09 14:58:36.777",
    "ECUId": "SIM_ECU_01",
    "ApID": "BCM",
    "CtID": "ACCESS",
    "SessionID": 1749488250,
    "Type": "LOG",
    "LogLevel": "DEBUG",
    "Payload": "Door lock actuators status: FL:L, FR:L, RL:L, RR:L."
  },
  {
    "Index": 78,
    "Timestamp": 1749481116.7789457,
    "Time": "2025-06-09 14:58:36.778",
    "ECUId": "SIM_ECU_01",
    "ApID": "BCM",
    "CtID": "ACCESS",
    "SessionID": 1749488250,
    "Type": "LOG",
    "LogLevel": "INFO",
    "Payload": "Unlocking all doors. Command: UNLOCK."
  },
  {
    "Index": 79,
    "Timestamp": 1749481116.7834494,
    "Time": "2025-06-09 14:58:36.783",
    "ECUId": "SIM_ECU_01",
    "ApID": "BCM",
    "CtID": "ACCESS",
    "SessionID": 1749488250,
    "Type": "LOG",
    "LogLevel": "DEBUG",
    "Payload": "Door lock actuators status: FL:U, FR:U, RL:U, RR:U."
  },
  {
    "Index": 80,
    "Timestamp": 1749481116.7951117,
    "Time": "2025-06-09 14:58:36.795",
    "ECUId": "SIM_ECU_01",
    "ApID": "BCM",
    "CtID": "ACCESS",
    "SessionID": 1749488250,
    "Type": "LOG",
    "LogLevel": "DEBUG",
    "Payload": "Checking door status sensors."
  },
  {
    "Index": 81,
    "Timestamp": 1749481116.8081317,
    "Time": "2025-06-09 14:58:36.808",
    "ECUId": "SIM_ECU_01",
    "ApID": "BCM",
    "CtID": "ACCESS",
    "SessionID": 1749488250,
    "Type": "LOG",
    "LogLevel": "DEBUG",
    "Payload": "Door status report: ALL_CLOSED_LOCKED."
  },
  {
    "Index": 82,
    "Timestamp": 1749481116.8121092,
    "Time": "2025-06-09 14:58:36.812",
    "ECUId": "SIM_ECU_01",
    "ApID": "BCM",
    "CtID": "ACCESS",
    "SessionID": 1749488250,
    "Type": "LOG",
    "LogLevel": "DEBUG",
    "Payload": "Door status report: FR_OPEN_UNLOCKED, others_CLOSED_UNLOCKED (Simulated)."
  },
  {
    "Index": 83,
    "Timestamp": 1749481116.8210232,
    "Time": "2025-06-09 14:58:36.821",
    "ECUId": "SIM_ECU_01",
    "ApID": "BCM",
    "CtID": "ACCESS",
    "SessionID": 1749488250,
    "Type": "LOG",
    "LogLevel": "WARN",
    "Payload": "Front Right door reported OPEN while system active."
  },
  {
    "Index": 84,
    "Timestamp": 1749481116.834451,
    "Time": "2025-06-09 14:58:36.834",
    "ECUId": "SIM_ECU_01",
    "ApID": "BCM",
    "CtID": "PROC",
    "SessionID": 1749488250,
    "Type": "LOG",
    "LogLevel": "DEBUG",
    "Payload": "Finished processing comfort requests for this cycle."
  },
  {
    "Index": 85,
    "Timestamp": 1749481116.8472278,
    "Time": "2025-06-09 14:58:36.847",
    "ECUId": "SIM_ECU_01",
    "ApID": "IHU",
    "CtID": "PROC",
    "SessionID": 1749488250,
    "Type": "LOG",
    "LogLevel": "WARN",
    "Payload": "ProcessUserInput: IHU not initialized. Skipping."
  },
  {
    "Index": 86,
    "Timestamp": 1749481116.8540895,
    "Time": "2025-06-09 14:58:36.854",
    "ECUId": "SIM_ECU_01",
    "ApID": "IHU",
    "CtID": "HMI",
    "SessionID": 1749488250,
    "Type": "LOG",
    "LogLevel": "DEBUG",
    "Payload": "User input: VolumeKnob UP. Target vol: 60pct."
  },
  {
    "Index": 87,
    "Timestamp": 1749481116.8630426,
    "Time": "2025-06-09 14:58:36.863",
    "ECUId": "SIM_ECU_01",
    "ApID": "IHU",
    "CtID": "AUDIO",
    "SessionID": 1749488250,
    "Type": "LOG",
    "LogLevel": "INFO",
    "Payload": "Volume level set to: 18 pct."
  },
  {
    "Index": 88,
    "Timestamp": 1749481116.8738835,
    "Time": "2025-06-09 14:58:36.873",
    "ECUId": "SIM_ECU_01",
    "ApID": "IHU",
    "CtID": "AUDIO",
    "SessionID": 1749488250,
    "Type": "LOG",
    "LogLevel": "INFO",
    "Payload": "Audio MUTED (volume is 0)."
  },
  {
    "Index": 89,
    "Timestamp": 1749481116.885849,
    "Time": "2025-06-09 14:58:36.885",
    "ECUId": "SIM_ECU_01",
    "ApID": "IHU",
    "CtID": "AUDIO",
    "SessionID": 1749488250,
    "Type": "LOG",
    "LogLevel": "WARN",
    "Payload": "Volume at MAX (100pct). Amplifier gain: 0dB (sim)."
  },
  {
    "Index": 90,
    "Timestamp": 1749481116.8906517,
    "Time": "2025-06-09 14:58:36.890",
    "ECUId": "SIM_ECU_01",
    "ApID": "IHU",
    "CtID": "HMI",
    "SessionID": 1749488250,
    "Type": "LOG",
    "LogLevel": "DEBUG",
    "Payload": "User input: VolumeKnob DOWN. Target vol: 40pct."
  },
  {
    "Index": 91,
    "Timestamp": 1749481116.8926914,
    "Time": "2025-06-09 14:58:36.892",
    "ECUId": "SIM_ECU_01",
    "ApID": "IHU",
    "CtID": "AUDIO",
    "SessionID": 1749488250,
    "Type": "LOG",
    "LogLevel": "INFO",
    "Payload": "Volume level set to: 96 pct."
  },
  {
    "Index": 92,
    "Timestamp": 1749481116.8938181,
    "Time": "2025-06-09 14:58:36.893",
    "ECUId": "SIM_ECU_01",
    "ApID": "IHU",
    "CtID": "AUDIO",
    "SessionID": 1749488250,
    "Type": "LOG",
    "LogLevel": "INFO",
    "Payload": "Audio MUTED (volume is 0)."
  },
  {
    "Index": 93,
    "Timestamp": 1749481116.9016533,
    "Time": "2025-06-09 14:58:36.901",
    "ECUId": "SIM_ECU_01",
    "ApID": "IHU",
    "CtID": "AUDIO",
    "SessionID": 1749488250,
    "Type": "LOG",
    "LogLevel": "WARN",
    "Payload": "Volume at MAX (100pct). Amplifier gain: 0dB (sim)."
  },
  {
    "Index": 94,
    "Timestamp": 1749481116.9136918,
    "Time": "2025-06-09 14:58:36.913",
    "ECUId": "SIM_ECU_01",
    "ApID": "IHU",
    "CtID": "HMI",
    "SessionID": 1749488250,
    "Type": "LOG",
    "LogLevel": "INFO",
    "Payload": "User input: Button NAV (ID 101). Switching to Nav."
  },
  {
    "Index": 95,
    "Timestamp": 1749481116.9262757,
    "Time": "2025-06-09 14:58:36.926",
    "ECUId": "SIM_ECU_01",
    "ApID": "IHU",
    "CtID": "HMI",
    "SessionID": 1749488250,
    "Type": "LOG",
    "LogLevel": "DEBUG",
    "Payload": "User input: Touchscreen press at X=320, Y=240 (Example values)."
  },
  {
    "Index": 96,
    "Timestamp": 1749481116.9320078,
    "Time": "2025-06-09 14:58:36.932",
    "ECUId": "SIM_ECU_01",
    "ApID": "IHU",
    "CtID": "HMI",
    "SessionID": 1749488250,
    "Type": "LOG",
    "LogLevel": "DEBUG",
    "Payload": "User input: Unhandled type/value. Type: 11, Value: 100."
  },
  {
    "Index": 97,
    "Timestamp": 1749481116.9379773,
    "Time": "2025-06-09 14:58:36.937",
    "ECUId": "SIM_ECU_01",
    "ApID": "IHU",
    "CtID": "HMI",
    "SessionID": 1749488250,
    "Type": "LOG",
    "LogLevel": "DEBUG",
    "Payload": "Updating display. Screen: 'Main Menu'. Widgets: 3. Brightness: 80pct (sim)."
  },
  {
    "Index": 98,
    "Timestamp": 1749481116.9463792,
    "Time": "2025-06-09 14:58:36.946",
    "ECUId": "SIM_ECU_01",
    "ApID": "IHU",
    "CtID": "HMI",
    "SessionID": 1749488250,
    "Type": "LOG",
    "LogLevel": "DEBUG",
    "Payload": "Display: Radio widget active. Info: Default Station. Signal: -65dBm."
  }
]