[
  {
    "Index": 1,
    "Timestamp": 1749480974.7587032,
    "Time": "2025-06-09 14:56:14.758",
    "ECUId": "SIM_ECU_01",
    "ApID": "SYSTEM",
    "CtID": "BOOT",
    "SessionID": 1749485538,
    "Type": "LOG",
    "LogLevel": "INFO",
    "Payload": "Dummy Automotive Application STARTING. Version: 1.0.1 (fixed)."
  },
  {
    "Index": 2,
    "Timestamp": 1749480974.7685366,
    "Time": "2025-06-09 14:56:14.768",
    "ECUId": "SIM_ECU_01",
    "ApID": "SYSTEM",
    "CtID": "BOOT",
    "SessionID": 1749485538,
    "Type": "LOG",
    "LogLevel": "INFO",
    "Payload": "App started with 27 arguments. First arg: 'argv [ 1 ]'."
  },
  {
    "Index": 3,
    "Timestamp": 1749480974.7740269,
    "Time": "2025-06-09 14:56:14.774",
    "ECUId": "SIM_ECU_01",
    "ApID": "SYSTEM",
    "CtID": "BOOT",
    "SessionID": 1749485538,
    "Type": "LOG",
    "LogLevel": "INFO",
    "Payload": "App started with no command-line arguments."
  },
  {
    "Index": 4,
    "Timestamp": 1749480974.7838576,
    "Time": "2025-06-09 14:56:14.783",
    "ECUId": "SIM_ECU_01",
    "ApID": "SYSTEM",
    "CtID": "MAIN",
    "SessionID": 1749485538,
    "Type": "LOG",
    "LogLevel": "DEBUG",
    "Payload": "Creating VehicleController instance..."
  },
  {
    "Index": 5,
    "Timestamp": 1749480974.7979786,
    "Time": "2025-06-09 14:56:14.797",
    "ECUId": "SIM_ECU_01",
    "ApID": "SYSTEM",
    "CtID": "MAIN",
    "SessionID": 1749485538,
    "Type": "LOG",
    "LogLevel": "DEBUG",
    "Payload": "VehicleController instance created."
  },
  {
    "Index": 6,
    "Timestamp": 1749480974.809768,
    "Time": "2025-06-09 14:56:14.809",
    "ECUId": "SIM_ECU_01",
    "ApID": "SYSTEM",
    "CtID": "MAIN",
    "SessionID": 1749485538,
    "Type": "LOG",
    "LogLevel": "INFO",
    "Payload": "Initiating system initialization sequence..."
  },
  {
    "Index": 7,
    "Timestamp": 1749480974.82313,
    "Time": "2025-06-09 14:56:14.823",
    "ECUId": "SIM_ECU_01",
    "ApID": "VCTRL",
    "CtID": "START",
    "SessionID": 1749485538,
    "Type": "LOG",
    "LogLevel": "INFO",
    "Payload": "Vehicle system initialization: STARTED."
  },
  {
    "Index": 8,
    "Timestamp": 1749480974.8278377,
    "Time": "2025-06-09 14:56:14.827",
    "ECUId": "SIM_ECU_01",
    "ApID": "VCTRL",
    "CtID": "PWR",
    "SessionID": 1749485538,
    "Type": "LOG",
    "LogLevel": "INFO",
    "Payload": "Performing Power-On Self-Test (POST)."
  },
  {
    "Index": 9,
    "Timestamp": 1749480974.8345969,
    "Time": "2025-06-09 14:56:14.834",
    "ECUId": "SIM_ECU_01",
    "ApID": "VCTRL",
    "CtID": "PWR",
    "SessionID": 1749485538,
    "Type": "LOG",
    "LogLevel": "DEBUG",
    "Payload": "Main ECU voltage: 12.6V (OK)."
  },
  {
    "Index": 10,
    "Timestamp": 1749480974.84701,
    "Time": "2025-06-09 14:56:14.847",
    "ECUId": "SIM_ECU_01",
    "ApID": "VCTRL",
    "CtID": "PWR",
    "SessionID": 1749485538,
    "Type": "LOG",
    "LogLevel": "DEBUG",
    "Payload": "CAN bus B termination: 60 Ohm (Nominal)."
  },
  {
    "Index": 11,
    "Timestamp": 1749480974.8484685,
    "Time": "2025-06-09 14:56:14.848",
    "ECUId": "SIM_ECU_01",
    "ApID": "VCTRL",
    "CtID": "PWR",
    "SessionID": 1749485538,
    "Type": "LOG",
    "LogLevel": "DEBUG",
    "Payload": "CAN bus A termination: 60 Ohm (Nominal)."
  },
  {
    "Index": 12,
    "Timestamp": 1749480974.853319,
    "Time": "2025-06-09 14:56:14.853",
    "ECUId": "SIM_ECU_01",
    "ApID": "VCTRL",
    "CtID": "PWR",
    "SessionID": 1749485538,
    "Type": "LOG",
    "LogLevel": "INFO",
    "Payload": "POST completed successfully."
  },
  {
    "Index": 13,
    "Timestamp": 1749480974.8571074,
    "Time": "2025-06-09 14:56:14.857",
    "ECUId": "SIM_ECU_01",
    "ApID": "VCTRL",
    "CtID": "START",
    "SessionID": 1749485538,
    "Type": "LOG",
    "LogLevel": "ERROR",
    "Payload": "ERROR: TCU init FAILED. Limited functionality."
  }
]