[
  {
    "Index": 1,
    "Timestamp": 1749481413.795759,
    "Time": "2025-06-09 15:03:33.795",
    "ECUId": "SIM_ECU_01",
    "ApID": "SYSTEM",
    "CtID": "BOOT",
    "SessionID": 1749483737,
    "Type": "LOG",
    "LogLevel": "INFO",
    "Payload": "Dummy Automotive Application STARTING. Version: 1.0.1 (fixed)."
  },
  {
    "Index": 2,
    "Timestamp": 1749481413.7984612,
    "Time": "2025-06-09 15:03:33.798",
    "ECUId": "SIM_ECU_01",
    "ApID": "SYSTEM",
    "CtID": "BOOT",
    "SessionID": 1749483737,
    "Type": "LOG",
    "LogLevel": "INFO",
    "Payload": "App started with 5 arguments. First arg: 'argv [ 1 ]'."
  },
  {
    "Index": 3,
    "Timestamp": 1749481413.8069613,
    "Time": "2025-06-09 15:03:33.806",
    "ECUId": "SIM_ECU_01",
    "ApID": "SYSTEM",
    "CtID": "BOOT",
    "SessionID": 1749483737,
    "Type": "LOG",
    "LogLevel": "INFO",
    "Payload": "App started with no command-line arguments."
  },
  {
    "Index": 4,
    "Timestamp": 1749481413.8137934,
    "Time": "2025-06-09 15:03:33.813",
    "ECUId": "SIM_ECU_01",
    "ApID": "SYSTEM",
    "CtID": "MAIN",
    "SessionID": 1749483737,
    "Type": "LOG",
    "LogLevel": "DEBUG",
    "Payload": "Creating VehicleController instance..."
  },
  {
    "Index": 5,
    "Timestamp": 1749481413.8247318,
    "Time": "2025-06-09 15:03:33.824",
    "ECUId": "SIM_ECU_01",
    "ApID": "SYSTEM",
    "CtID": "MAIN",
    "SessionID": 1749483737,
    "Type": "LOG",
    "LogLevel": "DEBUG",
    "Payload": "VehicleController instance created."
  },
  {
    "Index": 6,
    "Timestamp": 1749481413.8311098,
    "Time": "2025-06-09 15:03:33.831",
    "ECUId": "SIM_ECU_01",
    "ApID": "SYSTEM",
    "CtID": "MAIN",
    "SessionID": 1749483737,
    "Type": "LOG",
    "LogLevel": "INFO",
    "Payload": "Initiating system initialization sequence..."
  },
  {
    "Index": 7,
    "Timestamp": 1749481413.841991,
    "Time": "2025-06-09 15:03:33.841",
    "ECUId": "SIM_ECU_01",
    "ApID": "VCTRL",
    "CtID": "START",
    "SessionID": 1749483737,
    "Type": "LOG",
    "LogLevel": "INFO",
    "Payload": "Vehicle system initialization: STARTED."
  },
  {
    "Index": 8,
    "Timestamp": 1749481413.8504438,
    "Time": "2025-06-09 15:03:33.850",
    "ECUId": "SIM_ECU_01",
    "ApID": "VCTRL",
    "CtID": "PWR",
    "SessionID": 1749483737,
    "Type": "LOG",
    "LogLevel": "INFO",
    "Payload": "Performing Power-On Self-Test (POST)."
  },
  {
    "Index": 9,
    "Timestamp": 1749481413.8600726,
    "Time": "2025-06-09 15:03:33.860",
    "ECUId": "SIM_ECU_01",
    "ApID": "VCTRL",
    "CtID": "PWR",
    "SessionID": 1749483737,
    "Type": "LOG",
    "LogLevel": "DEBUG",
    "Payload": "Main ECU voltage: 12.6V (OK)."
  },
  {
    "Index": 10,
    "Timestamp": 1749481413.863877,
    "Time": "2025-06-09 15:03:33.863",
    "ECUId": "SIM_ECU_01",
    "ApID": "VCTRL",
    "CtID": "PWR",
    "SessionID": 1749483737,
    "Type": "LOG",
    "LogLevel": "DEBUG",
    "Payload": "CAN bus A termination: 60 Ohm (Nominal)."
  },
  {
    "Index": 11,
    "Timestamp": 1749481413.876974,
    "Time": "2025-06-09 15:03:33.876",
    "ECUId": "SIM_ECU_01",
    "ApID": "VCTRL",
    "CtID": "PWR",
    "SessionID": 1749483737,
    "Type": "LOG",
    "LogLevel": "DEBUG",
    "Payload": "CAN bus B termination: 60 Ohm (Nominal)."
  },
  {
    "Index": 12,
    "Timestamp": 1749481413.8906918,
    "Time": "2025-06-09 15:03:33.890",
    "ECUId": "SIM_ECU_01",
    "ApID": "VCTRL",
    "CtID": "PWR",
    "SessionID": 1749483737,
    "Type": "LOG",
    "LogLevel": "INFO",
    "Payload": "POST completed successfully."
  },
  {
    "Index": 13,
    "Timestamp": 1749481413.8945768,
    "Time": "2025-06-09 15:03:33.894",
    "ECUId": "SIM_ECU_01",
    "ApID": "VCTRL",
    "CtID": "START",
    "SessionID": 1749483737,
    "Type": "LOG",
    "LogLevel": "ERROR",
    "Payload": "ERROR: TCU init FAILED. Limited functionality."
  },
  {
    "Index": 14,
    "Timestamp": 1749481413.896118,
    "Time": "2025-06-09 15:03:33.896",
    "ECUId": "SIM_ECU_01",
    "ApID": "VCTRL",
    "CtID": "START",
    "SessionID": 1749483737,
    "Type": "LOG",
    "LogLevel": "ERROR",
    "Payload": "ERROR: ABS init FAILED."
  },
  {
    "Index": 15,
    "Timestamp": 1749481413.9087417,
    "Time": "2025-06-09 15:03:33.908",
    "ECUId": "SIM_ECU_01",
    "ApID": null,
    "CtID": null,
    "SessionID": 1749483737,
    "Type": "LOG",
    "LogLevel": null,
    "Payload": "An unexpected event occurred."
  },
  {
    "Index": 16,
    "Timestamp": 1749481413.9233062,
    "Time": "2025-06-09 15:03:33.923",
    "ECUId": "SIM_ECU_01",
    "ApID": "VCTRL",
    "CtID": "START",
    "SessionID": 1749483737,
    "Type": "LOG",
    "LogLevel": "ERROR",
    "Payload": "ERROR: BCM init FAILED."
  },
  {
    "Index": 17,
    "Timestamp": 1749481413.9257984,
    "Time": "2025-06-09 15:03:33.925",
    "ECUId": "SIM_ECU_01",
    "ApID": "VCTRL",
    "CtID": "START",
    "SessionID": 1749483737,
    "Type": "LOG",
    "LogLevel": "WARN",
    "Payload": "WARNING: IHU init FAILED. User experience affected."
  },
  {
    "Index": 18,
    "Timestamp": 1749481413.9384432,
    "Time": "2025-06-09 15:03:33.938",
    "ECUId": "SIM_ECU_01",
    "ApID": "VCTRL",
    "CtID": "START",
    "SessionID": 1749483737,
    "Type": "LOG",
    "LogLevel": "INFO",
    "Payload": "Vehicle system initialization: COMPLETED. State: RUNNING (2)."
  },
  {
    "Index": 19,
    "Timestamp": 1749481413.94756,
    "Time": "2025-06-09 15:03:33.947",
    "ECUId": "SIM_ECU_01",
    "ApID": "VCTRL",
    "CtID": "START",
    "SessionID": 1749483737,
    "Type": "LOG",
    "LogLevel": "ERROR",
    "Payload": "Vehicle system initialization: FAILED. State: ERROR (3). See logs."
  },
  {
    "Index": 20,
    "Timestamp": 1749481413.9516282,
    "Time": "2025-06-09 15:03:33.951",
    "ECUId": "SIM_ECU_01",
    "ApID": "VCTRL",
    "CtID": "NET",
    "SessionID": 1749483737,
    "Type": "LOG",
    "LogLevel": "INFO",
    "Payload": "Broadcasting network frame: System Active. Node ID: 0x01 (VCTRL)."
  },
  {
    "Index": 21,
    "Timestamp": 1749481413.9661536,
    "Time": "2025-06-09 15:03:33.966",
    "ECUId": "SIM_ECU_01",
    "ApID": "VCTRL",
    "CtID": "COMM",
    "SessionID": 1749483737,
    "Type": "LOG",
    "LogLevel": "DEBUG",
    "Payload": "Sending heartbeat on CAN Bus A. Cycle: 100ms (Simulated)."
  },
  {
    "Index": 22,
    "Timestamp": 1749481413.970577,
    "Time": "2025-06-09 15:03:33.970",
    "ECUId": "SIM_ECU_01",
    "ApID": "SYSTEM",
    "CtID": "MAIN",
    "SessionID": 1749483737,
    "Type": "LOG",
    "LogLevel": "INFO",
    "Payload": "System initialization sequence finished by VehicleController."
  },
  {
    "Index": 23,
    "Timestamp": 1749481413.9720907,
    "Time": "2025-06-09 15:03:33.972",
    "ECUId": "SIM_ECU_01",
    "ApID": "SYSTEM",
    "CtID": "MAIN",
    "SessionID": 1749483737,
    "Type": "LOG",
    "LogLevel": "INFO",
    "Payload": "Entering main application loop (simulated 2 iterations)."
  },
  {
    "Index": 24,
    "Timestamp": 1749481413.9767148,
    "Time": "2025-06-09 15:03:33.976",
    "ECUId": "SIM_ECU_01",
    "ApID": "SYSTEM",
    "CtID": "LOOP",
    "SessionID": 1749483737,
    "Type": "LOG",
    "LogLevel": "DEBUG",
    "Payload": "Main loop - Iteration #21."
  },
  {
    "Index": 25,
    "Timestamp": 1749481413.9852116,
    "Time": "2025-06-09 15:03:33.985",
    "ECUId": "SIM_ECU_01",
    "ApID": "VCTRL",
    "CtID": "LOOP",
    "SessionID": 1749483737,
    "Type": "LOG",
    "LogLevel": "WARN",
    "Payload": "Main loop skipped. System not init or not RUNNING. Current State val: 94."
  },
  {
    "Index": 26,
    "Timestamp": 1749481413.9876146,
    "Time": "2025-06-09 15:03:33.987",
    "ECUId": "SIM_ECU_01",
    "ApID": "VCTRL",
    "CtID": "LOOP",
    "SessionID": 1749483737,
    "Type": "LOG",
    "LogLevel": "DEBUG",
    "Payload": "Running main vehicle loop iteration. Vehicle State val: 44."
  },
  {
    "Index": 27,
    "Timestamp": 1749481413.9917612,
    "Time": "2025-06-09 15:03:33.991",
    "ECUId": "SIM_ECU_01",
    "ApID": "ECM",
    "CtID": "PROC",
    "SessionID": 1749483737,
    "Type": "LOG",
    "LogLevel": "WARN",
    "Payload": "ProcessEngineData: Module not initialized. Skipping."
  },
  {
    "Index": 28,
    "Timestamp": 1749481413.9979396,
    "Time": "2025-06-09 15:03:33.997",
    "ECUId": "SIM_ECU_01",
    "ApID": "ECM",
    "CtID": "PROC",
    "SessionID": 1749483737,
    "Type": "LOG",
    "LogLevel": "DEBUG",
    "Payload": "Processing Petrol engine data. Sim-RPM: 1500, Sim-Coolant: 85.5C."
  },
  {
    "Index": 29,
    "Timestamp": 1749481414.011566,
    "Time": "2025-06-09 15:03:34.011",
    "ECUId": "SIM_ECU_01",
    "ApID": "ECM",
    "CtID": "PROC",
    "SessionID": 1749483737,
    "Type": "LOG",
    "LogLevel": "DEBUG",
    "Payload": "Processing Diesel engine data. Sim-RPM: 1200, Sim-Coolant: 90.1C."
  },
  {
    "Index": 30,
    "Timestamp": 1749481414.0136132,
    "Time": "2025-06-09 15:03:34.013",
    "ECUId": "SIM_ECU_01",
    "ApID": "ECM",
    "CtID": "PROC",
    "SessionID": 1749483737,
    "Type": "LOG",
    "LogLevel": "DEBUG",
    "Payload": "Processing Electric motor data. Sim-Power: 25kW, Sim-BattTemp: 35.2C."
  },
  {
    "Index": 31,
    "Timestamp": 1749481414.0265489,
    "Time": "2025-06-09 15:03:34.026",
    "ECUId": "SIM_ECU_01",
    "ApID": "ECM",
    "CtID": "SENSOR",
    "SessionID": 1749483737,
    "Type": "LOG",
    "LogLevel": "DEBUG",
    "Payload": "Checking engine sensors. SimValues: O2=0.85V (Rich), MAF=15.2g/s (Nominal), Coolant=88.1C (Normal)."
  },
  {
    "Index": 32,
    "Timestamp": 1749481414.0354972,
    "Time": "2025-06-09 15:03:34.035",
    "ECUId": "SIM_ECU_01",
    "ApID": "ECM",
    "CtID": "SENSOR",
    "SessionID": 1749483737,
    "Type": "LOG",
    "LogLevel": "ERROR",
    "Payload": "CRITICAL: Engine overheating! Coolant Temp: 107.2C. Max Temp: 105.0C."
  },
  {
    "Index": 33,
    "Timestamp": 1749481414.0386796,
    "Time": "2025-06-09 15:03:34.038",
    "ECUId": "SIM_ECU_01",
    "ApID": "ECM",
    "CtID": "FUEL",
    "SessionID": 1749483737,
    "Type": "LOG",
    "LogLevel": "DEBUG",
    "Payload": "Fuel injection N/A for electric motor (Type 2)."
  },
  {
    "Index": 34,
    "Timestamp": 1749481414.0483744,
    "Time": "2025-06-09 15:03:34.048",
    "ECUId": "SIM_ECU_01",
    "ApID": "ECM",
    "CtID": "FUEL",
    "SessionID": 1749483737,
    "Type": "LOG",
    "LogLevel": "INFO",
    "Payload": "Enabling fuel injection. System: Common Rail."
  },
  {
    "Index": 35,
    "Timestamp": 1749481414.0554037,
    "Time": "2025-06-09 15:03:34.055",
    "ECUId": "SIM_ECU_01",
    "ApID": "ECM",
    "CtID": "FUEL",
    "SessionID": 1749483737,
    "Type": "LOG",
    "LogLevel": "INFO",
    "Payload": "Disabling fuel injection. Reason: Shutdown/Overheat."
  },
  {
    "Index": 36,
    "Timestamp": 1749481414.0564332,
    "Time": "2025-06-09 15:03:34.056",
    "ECUId": "SIM_ECU_01",
    "ApID": "ECM",
    "CtID": "FUEL",
    "SessionID": 1749483737,
    "Type": "LOG",
    "LogLevel": "WARN",
    "Payload": "Overheat protection: Fuel injection DISABLED."
  },
  {
    "Index": 37,
    "Timestamp": 1749481414.0696478,
    "Time": "2025-06-09 15:03:34.069",
    "ECUId": "SIM_ECU_01",
    "ApID": "ECM",
    "CtID": "SENSOR",
    "SessionID": 1749483737,
    "Type": "LOG",
    "LogLevel": "WARN",
    "Payload": "Engine temperature high: 98.5C. Normal Max: 95.0C."
  },
  {
    "Index": 38,
    "Timestamp": 1749481414.0804477,
    "Time": "2025-06-09 15:03:34.080",
    "ECUId": "SIM_ECU_01",
    "ApID": "ECM",
    "CtID": "IGNIT",
    "SessionID": 1749483737,
    "Type": "LOG",
    "LogLevel": "DEBUG",
    "Payload": "Ignition control N/A for electric motor (Type 2)."
  },
  {
    "Index": 39,
    "Timestamp": 1749481414.0873508,
    "Time": "2025-06-09 15:03:34.087",
    "ECUId": "SIM_ECU_01",
    "ApID": "ECM",
    "CtID": "IGNIT",
    "SessionID": 1749483737,
    "Type": "LOG",
    "LogLevel": "INFO",
    "Payload": "Enabling ignition system. Type: Coil-on-Plug."
  },
  {
    "Index": 40,
    "Timestamp": 1749481414.0959902,
    "Time": "2025-06-09 15:03:34.095",
    "ECUId": "SIM_ECU_01",
    "ApID": "ECM",
    "CtID": "IGNIT",
    "SessionID": 1749483737,
    "Type": "LOG",
    "LogLevel": "INFO",
    "Payload": "Disabling ignition system. Reason: Shutdown/Over-rev."
  },
  {
    "Index": 41,
    "Timestamp": 1749481414.106014,
    "Time": "2025-06-09 15:03:34.106",
    "ECUId": "SIM_ECU_01",
    "ApID": "ECM",
    "CtID": "IGNIT",
    "SessionID": 1749483737,
    "Type": "LOG",
    "LogLevel": "ERROR",
    "Payload": "Over-rev protection: Ignition system DISABLED."
  },
  {
    "Index": 42,
    "Timestamp": 1749481414.1087458,
    "Time": "2025-06-09 15:03:34.108",
    "ECUId": "SIM_ECU_01",
    "ApID": "ECM",
    "CtID": "PROC",
    "SessionID": 1749483737,
    "Type": "LOG",
    "LogLevel": "DEBUG",
    "Payload": "Updating engine actuators. SimActions: Throttle=15pct (Actual 14.8pct)."
  },
  {
    "Index": 43,
    "Timestamp": 1749481414.113771,
    "Time": "2025-06-09 15:03:34.113",
    "ECUId": "SIM_ECU_01",
    "ApID": "ECM",
    "CtID": "PROC",
    "SessionID": 1749483737,
    "Type": "LOG",
    "LogLevel": "INFO",
    "Payload": "Cooling fan command: ON (High Speed L2). SimCoolant: 96.0C."
  },
  {
    "Index": 44,
    "Timestamp": 1749481414.1212368,
    "Time": "2025-06-09 15:03:34.121",
    "ECUId": "SIM_ECU_01",
    "ApID": "ECM",
    "CtID": "PROC",
    "SessionID": 1749483737,
    "Type": "LOG",
    "LogLevel": "INFO",
    "Payload": "Cooling fan command: OFF. SimCoolant: 85.0C."
  },
  {
    "Index": 45,
    "Timestamp": 1749481414.1313276,
    "Time": "2025-06-09 15:03:34.131",
    "ECUId": "SIM_ECU_01",
    "ApID": "ECM",
    "CtID": "PROC",
    "SessionID": 1749483737,
    "Type": "LOG",
    "LogLevel": "DEBUG",
    "Payload": "Finished processing engine data. Cycle time: 10 ms (simulated)."
  },
  {
    "Index": 46,
    "Timestamp": 1749481414.1355941,
    "Time": "2025-06-09 15:03:34.135",
    "ECUId": "SIM_ECU_01",
    "ApID": "TCU",
    "CtID": "PROC",
    "SessionID": 1749483737,
    "Type": "LOG",
    "LogLevel": "WARN",
    "Payload": "ProcessTransmissionRequests: Module not initialized. Skipping."
  },
  {
    "Index": 47,
    "Timestamp": 1749481414.141088,
    "Time": "2025-06-09 15:03:34.141",
    "ECUId": "SIM_ECU_01",
    "ApID": "TCU",
    "CtID": "PROC",
    "SessionID": 1749483737,
    "Type": "LOG",
    "LogLevel": "DEBUG",
    "Payload": "Automatic: Processing shift logic. Sim-RPM: 2200, Sim-Speed: 60km/h."
  },
  {
    "Index": 48,
    "Timestamp": 1749481414.148957,
    "Time": "2025-06-09 15:03:34.148",
    "ECUId": "SIM_ECU_01",
    "ApID": "TCU",
    "CtID": "GEAR",
    "SessionID": 1749483737,
    "Type": "LOG",
    "LogLevel": "WARN",
    "Payload": "ShiftGearUp ignored. Reason: Not Auto or Not Initialized."
  },
  {
    "Index": 49,
    "Timestamp": 1749481414.1521332,
    "Time": "2025-06-09 15:03:34.152",
    "ECUId": "SIM_ECU_01",
    "ApID": "TCU",
    "CtID": "GEAR",
    "SessionID": 1749483737,
    "Type": "LOG",
    "LogLevel": "INFO",
    "Payload": "Shifted UP. New gear: 60."
  },
  {
    "Index": 50,
    "Timestamp": 1749481414.154136,
    "Time": "2025-06-09 15:03:34.154",
    "ECUId": "SIM_ECU_01",
    "ApID": "TCU",
    "CtID": "GEAR",
    "SessionID": 1749483737,
    "Type": "LOG",
    "LogLevel": "INFO",
    "Payload": "Already in highest gear (6). Shift up ignored."
  },
  {
    "Index": 51,
    "Timestamp": 1749481414.1562676,
    "Time": "2025-06-09 15:03:34.156",
    "ECUId": "SIM_ECU_01",
    "ApID": "TCU",
    "CtID": "GEAR",
    "SessionID": 1749483737,
    "Type": "LOG",
    "LogLevel": "DEBUG",
    "Payload": "Controlling shift solenoids for gear: 78."
  },
  {
    "Index": 52,
    "Timestamp": 1749481414.1657858,
    "Time": "2025-06-09 15:03:34.165",
    "ECUId": "SIM_ECU_01",
    "ApID": "TCU",
    "CtID": "GEAR",
    "SessionID": 1749483737,
    "Type": "LOG",
    "LogLevel": "DEBUG",
    "Payload": "Solenoid A: ON, Solenoid B: OFF (For Gear 1)."
  },
  {
    "Index": 53,
    "Timestamp": 1749481414.1711369,
    "Time": "2025-06-09 15:03:34.171",
    "ECUId": "SIM_ECU_01",
    "ApID": "TCU",
    "CtID": "PROC",
    "SessionID": 1749483737,
    "Type": "LOG",
    "LogLevel": "DEBUG",
    "Payload": "Manual: Awaiting gear shift. Clutch pos: 90pct (Engaged sim)."
  },
  {
    "Index": 54,
    "Timestamp": 1749481414.1782656,
    "Time": "2025-06-09 15:03:34.178",
    "ECUId": "SIM_ECU_01",
    "ApID": "TCU",
    "CtID": "HYDRAU",
    "SessionID": 1749483737,
    "Type": "LOG",
    "LogLevel": "ERROR",
    "Payload": "CRITICAL: Transmission oil OVERHEATING! Temp: 122.5C. Max: 120.0C."
  },
  {
    "Index": 55,
    "Timestamp": 1749481414.1862946,
    "Time": "2025-06-09 15:03:34.186",
    "ECUId": "SIM_ECU_01",
    "ApID": "TCU",
    "CtID": "STATE",
    "SessionID": 1749483737,
    "Type": "LOG",
    "LogLevel": "WARN",
    "Payload": "Transmission safe state requested. Forcing Neutral."
  },
  {
    "Index": 56,
    "Timestamp": 1749481414.1929295,
    "Time": "2025-06-09 15:03:34.192",
    "ECUId": "SIM_ECU_01",
    "ApID": "TCU",
    "CtID": "STATE",
    "SessionID": 1749483737,
    "Type": "LOG",
    "LogLevel": "INFO",
    "Payload": "Transmission now in Neutral (Safe State). SimOilTemp: 2.1C."
  },
  {
    "Index": 57,
    "Timestamp": 1749481414.199694,
    "Time": "2025-06-09 15:03:34.199",
    "ECUId": "SIM_ECU_01",
    "ApID": "TCU",
    "CtID": "HYDRAU",
    "SessionID": 1749483737,
    "Type": "LOG",
    "LogLevel": "WARN",
    "Payload": "Transmission oil temperature HIGH: 105.0C. Recommended Max: 100.0C."
  },
  {
    "Index": 58,
    "Timestamp": 1749481414.2028594,
    "Time": "2025-06-09 15:03:34.202",
    "ECUId": "SIM_ECU_01",
    "ApID": "TCU",
    "CtID": "PROC",
    "SessionID": 1749483737,
    "Type": "LOG",
    "LogLevel": "DEBUG",
    "Payload": "Finished processing transmission requests for this cycle."
  },
  {
    "Index": 59,
    "Timestamp": 1749481414.2089221,
    "Time": "2025-06-09 15:03:34.208",
    "ECUId": "SIM_ECU_01",
    "ApID": "ABS",
    "CtID": "PROC",
    "SessionID": 1749483737,
    "Type": "LOG",
    "LogLevel": "WARN",
    "Payload": "MonitorWheelSpeeds: Module not initialized. Skipping."
  },
  {
    "Index": 60,
    "Timestamp": 1749481414.2217572,
    "Time": "2025-06-09 15:03:34.221",
    "ECUId": "SIM_ECU_01",
    "ApID": "ABS",
    "CtID": "WHEEL",
    "SessionID": 1749483737,
    "Type": "LOG",
    "LogLevel": "DEBUG",
    "Payload": "Wheel Speeds (km/h): FL=50.2, FR=50.1, RL=49.8, RR=25.5 (Simulated)."
  },
  {
    "Index": 61,
    "Timestamp": 1749481414.2348487,
    "Time": "2025-06-09 15:03:34.234",
    "ECUId": "SIM_ECU_01",
    "ApID": "ABS",
    "CtID": "WHEEL",
    "SessionID": 1749483737,
    "Type": "LOG",
    "LogLevel": "WARN",
    "Payload": "Significant speed diff for RR wheel (25.5 km/h vs avg 50.1 km/h). Possible slippage/sensor issue."
  },
  {
    "Index": 62,
    "Timestamp": 1749481414.238892,
    "Time": "2025-06-09 15:03:34.238",
    "ECUId": "SIM_ECU_01",
    "ApID": "ABS",
    "CtID": "PUMP",
    "SessionID": 1749483737,
    "Type": "LOG",
    "LogLevel": "INFO",
    "Payload": "ABS Pump activated. Modulating brake pressure for RR wheel. Target slip: 15pct (sim)."
  },
  {
    "Index": 63,
    "Timestamp": 1749481414.2509928,
    "Time": "2025-06-09 15:03:34.250",
    "ECUId": "SIM_ECU_01",
    "ApID": "ABS",
    "CtID": "WHEEL",
    "SessionID": 1749483737,
    "Type": "LOG",
    "LogLevel": "INFO",
    "Payload": "Wheel speeds stabilized. ABS deactivated."
  },
  {
    "Index": 64,
    "Timestamp": 1749481414.265318,
    "Time": "2025-06-09 15:03:34.265",
    "ECUId": "SIM_ECU_01",
    "ApID": "ABS",
    "CtID": "STABIL",
    "SessionID": 1749483737,
    "Type": "LOG",
    "LogLevel": "INFO",
    "Payload": "ESP intervention: Understeer detected. Applying brake to FR wheel (20 bar sim)."
  },
  {
    "Index": 65,
    "Timestamp": 1749481414.2711368,
    "Time": "2025-06-09 15:03:34.271",
    "ECUId": "SIM_ECU_01",
    "ApID": "ABS",
    "CtID": "STABIL",
    "SessionID": 1749483737,
    "Type": "LOG",
    "LogLevel": "INFO",
    "Payload": "ESP system managing stability. Sim Sensors: Yaw=5.2deg/s, Steering=15deg."
  },
  {
    "Index": 66,
    "Timestamp": 1749481414.283292,
    "Time": "2025-06-09 15:03:34.283",
    "ECUId": "SIM_ECU_01",
    "ApID": "ABS",
    "CtID": "STABIL",
    "SessionID": 1749483737,
    "Type": "LOG",
    "LogLevel": "INFO",
    "Payload": "ESP intervention ended. Vehicle stable."
  },
  {
    "Index": 67,
    "Timestamp": 1749481414.2952704,
    "Time": "2025-06-09 15:03:34.295",
    "ECUId": "SIM_ECU_01",
    "ApID": "ABS",
    "CtID": "PROC",
    "SessionID": 1749483737,
    "Type": "LOG",
    "LogLevel": "DEBUG",
    "Payload": "Finished monitoring wheel speeds for this cycle."
  },
  {
    "Index": 68,
    "Timestamp": 1749481414.3092213,
    "Time": "2025-06-09 15:03:34.309",
    "ECUId": "SIM_ECU_01",
    "ApID": "BCM",
    "CtID": "PROC",
    "SessionID": 1749483737,
    "Type": "LOG",
    "LogLevel": "WARN",
    "Payload": "ProcessComfortRequests: BCM not initialized. Skipping."
  },
  {
    "Index": 69,
    "Timestamp": 1749481414.3104088,
    "Time": "2025-06-09 15:03:34.310",
    "ECUId": "SIM_ECU_01",
    "ApID": "BCM",
    "CtID": "PROC",
    "SessionID": 1749483737,
    "Type": "LOG",
    "LogLevel": "DEBUG",
    "Payload": "Processing comfort and access requests."
  },
  {
    "Index": 70,
    "Timestamp": 1749481414.3136606,
    "Time": "2025-06-09 15:03:34.313",
    "ECUId": "SIM_ECU_01",
    "ApID": "BCM",
    "CtID": "LIGHT",
    "SessionID": 1749483737,
    "Type": "LOG",
    "LogLevel": "INFO",
    "Payload": "Ambient light dark. Auto-activating headlights to ON (State 2)."
  },
  {
    "Index": 71,
    "Timestamp": 1749481414.319422,
    "Time": "2025-06-09 15:03:34.319",
    "ECUId": "SIM_ECU_01",
    "ApID": "BCM",
    "CtID": "LIGHT",
    "SessionID": 1749483737,
    "Type": "LOG",
    "LogLevel": "INFO",
    "Payload": "Headlights set to OFF (State 0)."
  },
  {
    "Index": 72,
    "Timestamp": 1749481414.3243287,
    "Time": "2025-06-09 15:03:34.324",
    "ECUId": "SIM_ECU_01",
    "ApID": "BCM",
    "CtID": "LIGHT",
    "SessionID": 1749483737,
    "Type": "LOG",
    "LogLevel": "INFO",
    "Payload": "Headlights set to PARKING (State 1)."
  },
  {
    "Index": 73,
    "Timestamp": 1749481414.3358436,
    "Time": "2025-06-09 15:03:34.335",
    "ECUId": "SIM_ECU_01",
    "ApID": "BCM",
    "CtID": "LIGHT",
    "SessionID": 1749483737,
    "Type": "LOG",
    "LogLevel": "INFO",
    "Payload": "Headlights set to ON (State 2 - Low Beam)."
  },
  {
    "Index": 74,
    "Timestamp": 1749481414.342327,
    "Time": "2025-06-09 15:03:34.342",
    "ECUId": "SIM_ECU_01",
    "ApID": "BCM",
    "CtID": "LIGHT",
    "SessionID": 1749483737,
    "Type": "LOG",
    "LogLevel": "WARN",
    "Payload": "Invalid headlight state requested: 50. No action."
  }
]